{
    "_comment": [
        "Clumps stale bread together into a shovel"
    ],
    "type": "minecraft:crafting_shaped",
    "group": "breadstone",
    "pattern": [
        " X ",
        " S ",
        " S "
    ],
    "key": {
        "S": {
            "item": "minecraft:stick",
            "data": 0
        },
        "X": {
            "item": "breadstone:stalebread",
            "data": 0
        }
    },
    "result": {
        "item": "breadstone:stalebreadshovel",
        "data": 0,
        "count": 1
    }
}